gazer/__init__.py
gazer/algorithms.py
gazer/base.py
gazer/core.py
gazer/correlation.py
gazer/ensembler.py
gazer/library.py
gazer/mcmc.py
gazer/metrics.py
gazer/sampling.py
gazer/utils.py
gazer/visualize.py
gazer/classifiers/__init__.py
gazer/classifiers/adaboost.py
gazer/classifiers/logistic_regression.py
gazer/classifiers/naive_bayes.py
gazer/classifiers/nearest_neighbors.py
gazer/classifiers/neural_network.py
gazer/classifiers/random_forest.py
gazer/classifiers/sgdescent.py
gazer/classifiers/svm.py
gazer/classifiers/tree.py
gazer/classifiers/xgb.py
gazer/externals/__init__.py
gazer/externals/clr_callback.py
gazer-0.1.dev1.dist-info/DESCRIPTION.rst
gazer-0.1.dev1.dist-info/METADATA
gazer-0.1.dev1.dist-info/RECORD
gazer-0.1.dev1.dist-info/WHEEL
gazer-0.1.dev1.dist-info/metadata.json
gazer-0.1.dev1.dist-info/top_level.txt
